resolute/__init__.py
resolute/resolute.py
resolute/test_result.py
resolute-0.9.2.dist-info/METADATA
resolute-0.9.2.dist-info/WHEEL
resolute-0.9.2.dist-info/top_level.txt
resolute-0.9.2.dist-info/RECORD
