Metadata-Version: 2.2
Name: resolute
Version: 0.9.2
Summary: Implementation of the Result pattern similar to C# ErrorOr package
Home-page: https://github.com/Marcurion/py-result-package
Author: Marcurion
Author-email: marcurion@private.com
Classifier: Programming Language :: Python :: 3
Classifier: License :: OSI Approved :: MIT License
Classifier: Operating System :: OS Independent
Requires-Python: >=3.11.11
Provides-Extra: dev
Requires-Dist: pytest; extra == "dev"
Dynamic: author
Dynamic: author-email
Dynamic: classifier
Dynamic: description
Dynamic: description-content-type
Dynamic: home-page
Dynamic: provides-extra
Dynamic: requires-python
Dynamic: summary
